LICENSE
MANIFEST.in
README.md
easydecon-logo.png
requirements.txt
setup.py
easydecon/__init__.py
easydecon/config.py
easydecon/easydecon.py
easydecon/extra.py
easydecon/modelling.py
easydecon/segmentation.py
easydecon.egg-info/PKG-INFO
easydecon.egg-info/SOURCES.txt
easydecon.egg-info/dependency_links.txt
easydecon.egg-info/entry_points.txt
easydecon.egg-info/not-zip-safe
easydecon.egg-info/requires.txt
easydecon.egg-info/top_level.txt
tests/test_easydecon.py