Metadata-Version: 2.1
Name: easydecon
Version: 0.1.2b1
Summary: easydecon
Home-page: https://github.com/sinanugur/easydecon
Author: Sinan U. Umu
Author-email: sinanugur@gmail.com
Keywords: scRNA single-cell high definition spatial transcriptomics deconvolution
Classifier: License :: OSI Approved :: MIT License
Classifier: Programming Language :: Python :: 3
Classifier: Topic :: Scientific/Engineering :: Bio-Informatics
License-File: LICENSE
